htdp_pt_br/__init__.py
htdp_pt_br/base.py
htdp_pt_br/image.py
htdp_pt_br/list.py
htdp_pt_br/universe.py
htdp_pt_br-0.1.4.dist-info/METADATA
htdp_pt_br-0.1.4.dist-info/RECORD
htdp_pt_br-0.1.4.dist-info/WHEEL
htdp_pt_br-0.1.4.dist-info/top_level.txt
