Metadata-Version: 2.1
Name: htdp-pt-br
Version: 0.1.4
Summary: A library and framework based on the HtDP approach for teaching programming, by Matthias Felleisen et al. It is similar to the htdp_pt_br packages in Racket.
Home-page: https://github.com/helioh2/htdp-python-pt-br.git
Author: Helio H. Monte-Alto
Author-email: heliohenrique3@gmail.com
License: UNKNOWN
Platform: UNKNOWN
Classifier: Programming Language :: Python :: 3
Classifier: License :: OSI Approved :: MIT License
Classifier: Operating System :: OS Independent
Requires-Dist: pygame
Requires-Dist: namedlist
